pytest_hot_test.py
hot_test_plugin/__init__.py
hot_test_plugin/dependency_tracker.py
hot_test_plugin/errors.py
hot_test_plugin/file_hash_manager.py
hot_test_plugin/message_handler.py
hot_test_plugin/session_manager.py
hot_test_plugin/settings.py
pytest_hot_test-0.1.1.dist-info/LICENSE
pytest_hot_test-0.1.1.dist-info/METADATA
pytest_hot_test-0.1.1.dist-info/WHEEL
pytest_hot_test-0.1.1.dist-info/entry_points.txt
pytest_hot_test-0.1.1.dist-info/top_level.txt
pytest_hot_test-0.1.1.dist-info/RECORD
